pydropcountr/__init__.py
pydropcountr/cli.py
pydropcountr/pydropcountr.py
pydropcountr-1.0.0.dist-info/METADATA
pydropcountr-1.0.0.dist-info/WHEEL
pydropcountr-1.0.0.dist-info/entry_points.txt
pydropcountr-1.0.0.dist-info/licenses/LICENSE
pydropcountr-1.0.0.dist-info/RECORD
