Metadata-Version: 2.4
Name: pydropcountr
Version: 1.0.0
Summary: Python library for interacting with DropCountr.com water usage monitoring
Project-URL: Homepage, https://github.com/mcolyer/pydropcountr
Project-URL: Repository, https://github.com/mcolyer/pydropcountr
Project-URL: Issues, https://github.com/mcolyer/pydropcountr/issues
Project-URL: Changelog, https://github.com/mcolyer/pydropcountr/blob/main/CHANGELOG.md
Author-email: Matthew Colyer <matt@colyer.name>
Maintainer-email: Matthew Colyer <matt@colyer.name>
License: MIT
License-File: LICENSE
Keywords: api,dropcountr,monitoring,usage,utilities,water
Classifier: Development Status :: 5 - Production/Stable
Classifier: Intended Audience :: Developers
Classifier: License :: OSI Approved :: MIT License
Classifier: Operating System :: OS Independent
Classifier: Programming Language :: Python :: 3
Classifier: Programming Language :: Python :: 3.12
Classifier: Programming Language :: Python :: 3.13
Classifier: Topic :: Home Automation
Classifier: Topic :: Internet :: WWW/HTTP :: Dynamic Content
Classifier: Topic :: Software Development :: Libraries :: Python Modules
Classifier: Topic :: Utilities
Requires-Python: >=3.12
Requires-Dist: fire>=0.7.0
Requires-Dist: pydantic>=2.0.0
Requires-Dist: requests>=2.31.0
Provides-Extra: dev
Requires-Dist: mypy>=1.0.0; extra == 'dev'
Requires-Dist: pytest>=7.0.0; extra == 'dev'
Requires-Dist: ruff>=0.1.0; extra == 'dev'
